{
  "display": {
    "icon": {
      "item": "minecraft:oak_log"
    },
    "title": "Serious Choppage",
    "description": "Collect 16 logs\n▶ Island\n▶ Wrench"
  },
  "parent": "skymode4:wooden_age/root",
  "criteria": {
    "pickup": {
      "trigger": "minecraft:inventory_changed",
      "conditions": {
        "items": [
          {
            "item": "minecraft:oak_log",
            "count": {
              "min":16
            }
          }
        ]
      }
    }
  },
  "rewards": {
    "function": "skymode4:advancements/reward/wooden_age/stack_logs"
  }
}
